apisoptimizer/__init__.py
apisoptimizer/bee.py
apisoptimizer/colony.py
apisoptimizer/parameter.py
apisoptimizer/utils.py
apisoptimizer-1.0.1.dist-info/LICENSE.txt
apisoptimizer-1.0.1.dist-info/METADATA
apisoptimizer-1.0.1.dist-info/WHEEL
apisoptimizer-1.0.1.dist-info/top_level.txt
apisoptimizer-1.0.1.dist-info/RECORD
