Metadata-Version: 2.1
Name: apisoptimizer
Version: 1.0.1
Summary: Artificial bee colony framework for tuning variables in user-suppled functions
Home-page: http://github.com/tjkessler/apisoptimizer
Author: Travis Kessler
Author-email: travis.j.kessler@gmail.com
License: MIT
Platform: UNKNOWN
